{
  "Straumann Bone Level NC 3.3": "L9000-R",
  "Mis C1 NP": "L9000-R",
  "Osstem Mini": "L9000-R",
  "Ankylos C": "L9000-R",
  "Straumann Bone Level RC 4.1": "L9010-R",
  "Astra Tech 4.5": "S9020-R",
  "Astra Tech 5.0": "S9020-R",
  "Nobel Active NP(3,5)": "F9010-R",
  "Nobel Active RP(4,3)": "F9000-R",
  "Nobel Active RP(5,0)": "F9000-R",
  "MIC C1 WP": "R9010-R",
  "MIS SP 3.5": "R9000-R",
  "IMPLANTIUM": "R9000-R",
  "Osstem Regular": "R9000-R",
  "Mis C1 SP": "R9000-R",
  "Conmet 2.7": "R9000-R",
  "Dio RP": "R9000-R",
  "Liko-M": "R9000-R",
  "Nobel Rep RP 4.3": "E9010-R",
  "Nobel Rep WP 5.0": "E9020-R",
  "Xive 3.4": "T9000-R",
  "Xive 3.8": "T9005-R",
  "Xive 4.5": "T9010-R",
  "Nobel Rep NP 3.5": "E9000-R",
  "Straumann SynOcta WN 6.5": "N9020-R",
  "ICX": "CX9000-R",
  "Straumann SynOcta RN 4.8": "N9010-R",
  "Astra Tech 3.5": "S9000-R",
  "Astra Tech 4.0": "S9000-R",
  "SKY Bredent": "B9000-R",
  "Astra Tech 3.0": "S9030-R"
}